{
    "ad1": {
      "title": "Admin D1",
      "themeColor": "#FFD700",
      "logo": "/logos/d1.svg"
    },
    "ad2": {
      "title": "Admin D2",
      "themeColor": "#00BFFF",
      "logo": "/logos/d2.svg"
    },
    "ad3": {
      "title": "Admin D3",
      "themeColor": "#98FB98",
      "logo": "/logos/d3.svg"
    },
    "ad4": {
      "title": "Admin D4",
      "themeColor": "#FFD700",
      "logo": "/logos/d1.svg"
    },
    "ad5": {
      "title": "Admin D5",
      "themeColor": "#00BFFF",
      "logo": "/logos/d2.svg"
    },
    "ad6": {
      "title": "Admin D6",
      "themeColor": "#98FB98",
      "logo": "/logos/d3.svg"
    }
    
  }
  